deutschland/weiterbildungssuche/__init__.py
deutschland/weiterbildungssuche/api/__init__.py
deutschland/weiterbildungssuche/api/default_api.py
deutschland/weiterbildungssuche/api_client.py
deutschland/weiterbildungssuche/apis/__init__.py
deutschland/weiterbildungssuche/configuration.py
deutschland/weiterbildungssuche/exceptions.py
deutschland/weiterbildungssuche/model/__init__.py
deutschland/weiterbildungssuche/model/response.py
deutschland/weiterbildungssuche/model/response_aggregations.py
deutschland/weiterbildungssuche/model/response_aggregations_anzahlausgefiltert.py
deutschland/weiterbildungssuche/model/response_aggregations_anzahlgesamt.py
deutschland/weiterbildungssuche/model/response_aggregations_lernformen.py
deutschland/weiterbildungssuche/model/response_aggregations_regionen.py
deutschland/weiterbildungssuche/model/response_aggregations_unterrichstzeit.py
deutschland/weiterbildungssuche/model/response_embedded.py
deutschland/weiterbildungssuche/model/response_embedded_adresse.py
deutschland/weiterbildungssuche/model/response_embedded_adresse_koordinaten.py
deutschland/weiterbildungssuche/model/response_embedded_adresse_ort_stra_e.py
deutschland/weiterbildungssuche/model/response_embedded_adresse_ort_stra_e_land.py
deutschland/weiterbildungssuche/model/response_embedded_angebot.py
deutschland/weiterbildungssuche/model/response_embedded_ansprechpartner.py
deutschland/weiterbildungssuche/model/response_embedded_dauer.py
deutschland/weiterbildungssuche/model/response_embedded_rollen.py
deutschland/weiterbildungssuche/model/response_embedded_termine.py
deutschland/weiterbildungssuche/model/response_embedded_unterrichtsform.py
deutschland/weiterbildungssuche/model/response_embedded_unterrichtszeit.py
deutschland/weiterbildungssuche/model/response_links.py
deutschland/weiterbildungssuche/model/response_links_first.py
deutschland/weiterbildungssuche/model/response_links_last.py
deutschland/weiterbildungssuche/model/response_links_next.py
de_weiterbildungssuche-0.1.0.dist-info/WHEEL
de_weiterbildungssuche-0.1.0.dist-info/METADATA
de_weiterbildungssuche-0.1.0.dist-info/RECORD
